{
	"info": {
		"_postman_id": "a12bf5b8-9e3d-46d6-9745-0fc17fe4f5fa",
		"name": "api-empleados",
		"schema": "https://schema.getpostman.com/json/collection/v2.1.0/collection.json"
	},
	"item": [
		{
			"name": "guardar empleado",
			"request": {
				"method": "POST",
				"header": [],
				"body": {
					"mode": "raw",
					"raw": "{\n    \"fechaIngreso\": \"2022-12-22\",\n    \"nombre\": \"jose silva\",\n    \"salario\": 5000000\n}",
					"options": {
						"raw": {
							"language": "json"
						}
					}
				},
				"url": {
					"raw": "http://localhost:8080/api/v1/empleados/guardar-empleado",
					"protocol": "http",
					"host": [
						"localhost"
					],
					"port": "8080",
					"path": [
						"api",
						"v1",
						"empleados",
						"guardar-empleado"
					]
				}
			},
			"response": []
		},
		{
			"name": "guardar solicitud",
			"request": {
				"method": "POST",
				"header": [],
				"body": {
					"mode": "raw",
					"raw": "{\n    \"descripcion\": \"solicitud 2\",\n    \"resumen\": \"solicitud 2 CI\",\n    \"empleado\": {\n        \"id\": 3,\n        \"fechaIngreso\": \"2022-12-20\",\n        \"nombre\": \"Camilo Giraldo velez\",\n        \"salario\": 1000000\n    }\n}",
					"options": {
						"raw": {
							"language": "json"
						}
					}
				},
				"url": {
					"raw": "http://localhost:8080/api/v1/solicitudes/crear-solicitud",
					"protocol": "http",
					"host": [
						"localhost"
					],
					"port": "8080",
					"path": [
						"api",
						"v1",
						"solicitudes",
						"crear-solicitud"
					]
				}
			},
			"response": []
		},
		{
			"name": "lista empleados",
			"protocolProfileBehavior": {
				"disableBodyPruning": true
			},
			"request": {
				"method": "GET",
				"header": [],
				"body": {
					"mode": "raw",
					"raw": "",
					"options": {
						"raw": {
							"language": "json"
						}
					}
				},
				"url": {
					"raw": "http://localhost:8080/api/v1/empleados/lista",
					"protocol": "http",
					"host": [
						"localhost"
					],
					"port": "8080",
					"path": [
						"api",
						"v1",
						"empleados",
						"lista"
					]
				}
			},
			"response": []
		},
		{
			"name": "lista solicitudes",
			"protocolProfileBehavior": {
				"disableBodyPruning": true
			},
			"request": {
				"method": "GET",
				"header": [],
				"body": {
					"mode": "raw",
					"raw": "",
					"options": {
						"raw": {
							"language": "json"
						}
					}
				},
				"url": {
					"raw": "http://localhost:8080/api/v1/solicitudes/lista",
					"protocol": "http",
					"host": [
						"localhost"
					],
					"port": "8080",
					"path": [
						"api",
						"v1",
						"solicitudes",
						"lista"
					]
				}
			},
			"response": []
		},
		{
			"name": "buscar solicitud",
			"protocolProfileBehavior": {
				"disableBodyPruning": true
			},
			"request": {
				"method": "GET",
				"header": [],
				"body": {
					"mode": "raw",
					"raw": "",
					"options": {
						"raw": {
							"language": "json"
						}
					}
				},
				"url": {
					"raw": "http://localhost:8080/api/v1/solicitudes/buscar-solicitud/3e9d4160-6333-432e-85cd-122eda9fb0f4",
					"protocol": "http",
					"host": [
						"localhost"
					],
					"port": "8080",
					"path": [
						"api",
						"v1",
						"solicitudes",
						"buscar-solicitud",
						"3e9d4160-6333-432e-85cd-122eda9fb0f4"
					]
				}
			},
			"response": []
		},
		{
			"name": "buscar empleado",
			"protocolProfileBehavior": {
				"disableBodyPruning": true
			},
			"request": {
				"method": "GET",
				"header": [],
				"body": {
					"mode": "raw",
					"raw": "",
					"options": {
						"raw": {
							"language": "json"
						}
					}
				},
				"url": {
					"raw": "http://localhost:8080/api/v1/empleados/buscar-empleado/3",
					"protocol": "http",
					"host": [
						"localhost"
					],
					"port": "8080",
					"path": [
						"api",
						"v1",
						"empleados",
						"buscar-empleado",
						"3"
					]
				}
			},
			"response": []
		},
		{
			"name": "actualizar empleado",
			"request": {
				"method": "PUT",
				"header": [],
				"body": {
					"mode": "raw",
					"raw": "{\n    \"id\": 2,\n    \"fechaIngreso\": \"2022-12-20\",\n    \"nombre\": \"Camilo Giraldo velez\",\n    \"salario\": 1000000\n}",
					"options": {
						"raw": {
							"language": "json"
						}
					}
				},
				"url": {
					"raw": "http://localhost:8080/api/v1/empleados/actualizar-empleado",
					"protocol": "http",
					"host": [
						"localhost"
					],
					"port": "8080",
					"path": [
						"api",
						"v1",
						"empleados",
						"actualizar-empleado"
					]
				}
			},
			"response": []
		}
	]
}